secure_ai_toolset/__init__.py
secure_ai_toolset/secrets/__init__.py
secure_ai_toolset/secrets/aws_secrets_manager_provider.py
secure_ai_toolset/secrets/conjur_secrets_provider.py
secure_ai_toolset/secrets/environment_manager.py
secure_ai_toolset/secrets/file_secrets_provider.py
secure_ai_toolset/secrets/secrets_provider.py
secure_ai_toolset-0.1.1.dist-info/LICENSE
secure_ai_toolset-0.1.1.dist-info/METADATA
secure_ai_toolset-0.1.1.dist-info/NOTICES.txt
secure_ai_toolset-0.1.1.dist-info/WHEEL
secure_ai_toolset-0.1.1.dist-info/RECORD
