Metadata-Version: 2.3
Name: secure-ai-toolset
Version: 0.1.1
Summary: python toolset to secure AI agents with secret provisioning, authentication, call monitoring and authorization
License: Apache Software License (Apache-2.0)
Author: CyberArk
Author-email: acyberark@cyberark.com
Requires-Python: >=3.10.0,<4.0
Classifier: License :: Other/Proprietary License
Classifier: Programming Language :: Python :: 3
Classifier: Programming Language :: Python :: 3.10
Classifier: Programming Language :: Python :: 3.11
Classifier: Programming Language :: Python :: 3.12
Classifier: Programming Language :: Python :: 3.13
Requires-Dist: boto3
Requires-Dist: python-dotenv (>=1.0.1,<2.0.0)
Requires-Dist: requests (>=2.32.3,<3.0.0)
